diff_and_patch/__init__.py
diff_and_patch/delta.py
diff_and_patch/exceptions.py
diff_and_patch/tests.py
diff_and_patch/utils.py
diff_and_patch/validator.py
diff_and_patch/diff/__init__.py
diff_and_patch/diff/diff_item.py
diff_and_patch/diff/differ.py
diff_and_patch/patch/__init__.py
diff_and_patch/patch/patch_item.py
diff_and_patch/patch/patcher.py
diff_and_patch-0.1.0.dist-info/DESCRIPTION.rst
diff_and_patch-0.1.0.dist-info/METADATA
diff_and_patch-0.1.0.dist-info/RECORD
diff_and_patch-0.1.0.dist-info/WHEEL
diff_and_patch-0.1.0.dist-info/metadata.json
diff_and_patch-0.1.0.dist-info/top_level.txt
